LICENSE.md
MANIFEST.in
requirements.txt
setup.py
uspech/__init__.py
uspech/exceptions.py
uspech/log.py
uspech/rbac.py
uspech/sqlsoup.py
uspech.egg-info/PKG-INFO
uspech.egg-info/SOURCES.txt
uspech.egg-info/dependency_links.txt
uspech.egg-info/not-zip-safe
uspech.egg-info/requires.txt
uspech.egg-info/top_level.txt
uspech/zeromq/__init__.py
uspech/zeromq/router.py