Metadata-Version: 1.1
Name: uspech
Version: 0.3.1
Summary: Common project utilities (not for general use)
Home-page: http://github.com/singularita/uspech/
Author: Singularita s.r.o.
Author-email: UNKNOWN
License: MIT
Keywords: utilities
Platform: UNKNOWN
Classifier: Development Status :: 2 - Pre-Alpha
Classifier: Programming Language :: Python :: 3 :: Only
Classifier: License :: OSI Approved :: MIT License
Classifier: Intended Audience :: Developers
